french_color_to_hex/__init__.py
french_color_to_hex/colors.json
french_color_to_hex/get_color_code.py
french_color_to_hex-0.1.6.dist-info/METADATA
french_color_to_hex-0.1.6.dist-info/WHEEL
french_color_to_hex-0.1.6.dist-info/top_level.txt
french_color_to_hex-0.1.6.dist-info/RECORD
