Metadata-Version: 2.1
Name: french-color-to-hex
Version: 0.1.6
Requires-Dist: unidecode
